snowflake_sql_api_client/__init__.py
snowflake_sql_api_client/api_client.py
snowflake_sql_api_client/configuration.py
snowflake_sql_api_client/rest.py
snowflake_sql_api_client/api/__init__.py
snowflake_sql_api_client/api/apiv2statements__statement_handle_api.py
snowflake_sql_api_client/api/apiv2statements_api.py
snowflake_sql_api_client/models/__init__.py
snowflake_sql_api_client/utilities/__init__.py
snowflake_sql_api_client/utilities/sql_api_generate_jwt.py
snowflake_sql_api_client/utilities/sql_api_utils.py
test/__init__.py
test/test_apiv2statements__statement_handle_api.py
test/test_apiv2statements_api.py
snowflake_sql_api_client-2.0.6.dist-info/LICENSE.txt
snowflake_sql_api_client-2.0.6.dist-info/METADATA
snowflake_sql_api_client-2.0.6.dist-info/WHEEL
snowflake_sql_api_client-2.0.6.dist-info/top_level.txt
snowflake_sql_api_client-2.0.6.dist-info/RECORD
