Metadata-Version: 2.1
Name: snowflake-sql-api-client
Version: 2.0.6
Summary: Snowflake SQL API V2
Home-page: https://github.com/nqtung/snowflake-sql-api-pyclient
Author-email: tungnq@gmail.com
Keywords: Snowflake SQL API V2
License-File: LICENSE.txt
Requires-Dist: urllib3 (>=1.15)
Requires-Dist: six (>=1.10)
Requires-Dist: certifi
Requires-Dist: python-dateutil
Requires-Dist: pyjwt
Requires-Dist: cryptography
